{
    "id": "radioactivity-concentration-of-84Br-in-air",
    "validation-key": "radioactivity-concentration-of-84br-in-air",
    "ui-label": "Radioactivity Concentration Of 84br In Air",
    "description": "\"Radioactivity\" means the number of radioactive decays of a material per second. \"Radioactivity concentration\" means radioactivity per unit volume of the medium. \"Br\" means the element \"bromine\" and \"84Br\" is the isotope \"bromine-84\" with a half-life of 2.21e-02 days.",
    "canonical_units": "Bq m-3",
    "cf-name": "radioactivity_concentration_of_84Br_in_air",
    "@context": "_context_",
    "type": [
        "wcrp:standard-name",
        "cf"
    ]
}
