{
    "id": "surface-radioactivity-content-of-128mSb",
    "validation-key": "surface-radioactivity-content-of-128msb",
    "ui-label": "Surface Radioactivity Content Of 128msb",
    "description": "The surface called \"surface\" means the lower boundary of the atmosphere. \"Content\" indicates a quantity per unit area. \"Radioactivity\" means the number of radioactive decays of a material per second. \"Sb\" means the element \"antimony\" and \"128mSb\" is the metastable state of the isotope \"antimony-128\" with a half-life of 7.23e-03 days.",
    "canonical_units": "Bq m-2",
    "cf-name": "surface_radioactivity_content_of_128mSb",
    "@context": "_context_",
    "type": [
        "wcrp:standard-name",
        "cf"
    ]
}
