{
  "@id": "cf:standard_name/radioactivity_concentration_of_124mSb_in_air",
  "@type": "standard-name",
  "name": "radioactivity_concentration_of_124mSb_in_air",
  "description": "\"Radioactivity\" means the number of radioactive decays of a material per second. \"Radioactivity concentration\" means radioactivity per unit volume of the medium. \"Sb\" means the element \"antimony\" and \"124mSb\" is the metastable state of the isotope \"antimony-124\" with a half-life of 1.41e-02 days.",
  "canonical_units": "Bq m-3",
  "amip": null,
  "grib": null
}